l0n0lsimple/HttpServer.py
l0n0lsimple/Image2Base64.py
l0n0lsimple/KVServer.py
l0n0lsimple/SystemctlGui.py
l0n0lsimple/SystemctlTerminal.py
l0n0lsimple/__init__.py
l0n0lsimple-0.4.5.dist-info/METADATA
l0n0lsimple-0.4.5.dist-info/WHEEL
l0n0lsimple-0.4.5.dist-info/entry_points.txt
l0n0lsimple-0.4.5.dist-info/top_level.txt
l0n0lsimple-0.4.5.dist-info/RECORD
