Metadata-Version: 2.1
Name: l0n0lsimple
Version: 0.4.5
Summary: 一些简单好用的命令
Requires-Python: >=3.8
Requires-Dist: aiohttp
